postomc/__init__.py
postomc/data.py
postomc/depletion_results.py
postomc/CLI/cli.py
postomc/CLI/export.py
postomc/CLI/info.py
postomc/CLI/plot.py
postomc-0.4.0.dist-info/METADATA
postomc-0.4.0.dist-info/WHEEL
postomc-0.4.0.dist-info/entry_points.txt
postomc-0.4.0.dist-info/top_level.txt
postomc-0.4.0.dist-info/RECORD
