Metadata-Version: 2.4
Name: postomc
Version: 0.4.0
Summary: A package to read and analyze OpenMC's `depletion_results.h5` files.
Author-email: Nicolas Linden <nicolas@nlinden.com>
Requires-Python: >=3.11
Requires-Dist: click>=8.1.8
Requires-Dist: h5py>=3.12.1
Requires-Dist: matplotlib>=3.10.5
Requires-Dist: numpy>=2.2.2
Requires-Dist: pandas>=2.2.3
Requires-Dist: pint>=0.24.4
Requires-Dist: rich>=14.1.0
Requires-Dist: uncertainties>=3.2.2
Requires-Dist: xlsxwriter>=3.2.2
